canonical_range.py
canonical_range-0.1.0a2.dist-info/licenses/LICENSE
canonical_range-0.1.0a2.dist-info/METADATA
canonical_range-0.1.0a2.dist-info/WHEEL
canonical_range-0.1.0a2.dist-info/top_level.txt
canonical_range-0.1.0a2.dist-info/RECORD
