Metadata-Version: 2.4
Name: canonical-range
Version: 0.1.0a2
Summary: A Python implementation of a **canonical range** (where `step != 0, length >= 0, stop == start + length * step`) with enhanced functionality compared to Python's built-in `range`.
Author-email: Jifeng Wu <jifengwu2k@gmail.com>
License-Expression: MIT
Project-URL: Homepage, https://github.com/jifengwu2k/canonical-range
Project-URL: Bug Tracker, https://github.com/jifengwu2k/canonical-range/issues
Classifier: Programming Language :: Python :: 2
Classifier: Programming Language :: Python :: 3
Classifier: Operating System :: OS Independent
Requires-Python: >=2
License-File: LICENSE
Requires-Dist: canonical-interval
Requires-Dist: typing; python_version < "3.5"
Dynamic: license-file
